txmx/__init__.py
txmx-0.0.1.dist-info/METADATA
txmx-0.0.1.dist-info/RECORD
txmx-0.0.1.dist-info/WHEEL
txmx-0.0.1.dist-info/top_level.txt
